blazeform/__init__.py
blazeform/element.py
blazeform/exceptions.py
blazeform/file_upload_translators.py
blazeform/form.py
blazeform/processors.py
blazeform/render.py
blazeform/util.py
blazeform/version.py
blazeform/tests/__init__.py
blazeform/tests/test_elements.py
blazeform/tests/test_elements_static.py
blazeform/tests/test_exceptions.py
blazeform/tests/test_form.py
blazeform/tests/test_processors.py
blazeform/tests/test_renderers.py
blazeform/tests/test_utils.py
blazeform/tests/renderers/__init__.py
blazeform/tests/renderers/all_els.html
blazeform/tests/renderers/all_els.py
blazeform/tests/renderers/default.html
blazeform/tests/renderers/default.py
blazeform/tests/renderers/noteprefix.html
blazeform/tests/renderers/noteprefix.py
blazeform/tests/renderers/reqnote.html
blazeform/tests/renderers/reqnote.py
blazeform/tests/renderers/reqnote_formtop.html
blazeform/tests/renderers/reqnote_formtop.py
blazeform/tests/renderers/reqnote_formtop_header.html
blazeform/tests/renderers/reqnote_formtop_header.py
blazeform/tests/renderers/reqnote_section.html
blazeform/tests/renderers/reqnote_section.py
blazeform/tests/renderers/static.html
blazeform/tests/renderers/static.py
blazeform/tests/renderers/withaction.html
blazeform/tests/renderers/withaction.py
BlazeForm-0.5.1.dist-info/METADATA
BlazeForm-0.5.1.dist-info/WHEEL
BlazeForm-0.5.1.dist-info/top_level.txt
BlazeForm-0.5.1.dist-info/RECORD
