Metadata-Version: 2.1
Name: BlazeForm
Version: 0.5.1
Summary: A library for generating and validating HTML forms
Home-page: https://github.com/blazelibs/blazeform
Author: Randy Syring
Author-email: randy.syring@level12.io
License: BSD
Platform: UNKNOWN
Classifier: Development Status :: 4 - Beta
Classifier: Intended Audience :: Developers
Classifier: License :: OSI Approved :: BSD License
Classifier: Operating System :: OS Independent
Classifier: Programming Language :: Python :: 3.7
Classifier: Programming Language :: Python :: 3.8
Classifier: Topic :: Internet :: WWW/HTTP
Requires-Dist: FormEncode (>=1.3.1)
Requires-Dist: BlazeUtils (>=0.6.2)
Requires-Dist: WebHelpers2
Provides-Extra: test
Requires-Dist: codecov ; extra == 'test'
Requires-Dist: coverage ; extra == 'test'
Requires-Dist: dnspython ; extra == 'test'
Requires-Dist: flake8 ; extra == 'test'
Requires-Dist: nose ; extra == 'test'
Requires-Dist: tox ; extra == 'test'
Requires-Dist: wheel ; extra == 'test'
